terminal_debian/__init__.py
terminal_debian/apt.py
terminal_debian/menu.py
terminal_debian/style.py
terminal_debian/users.py
terminal_debian/utils.py
terminal_debian/drives/__init__.py
terminal_debian/drives/common.py
terminal_debian/drives/drive.py
terminal_debian/drives/logical_volume.py
terminal_debian/drives/volume_group.py
terminal_debian-1.7.4.dist-info/METADATA
terminal_debian-1.7.4.dist-info/WHEEL
terminal_debian-1.7.4.dist-info/top_level.txt
terminal_debian-1.7.4.dist-info/zip-safe
terminal_debian-1.7.4.dist-info/RECORD
