Metadata-Version: 2.1
Name: terminal-debian
Version: 1.7.4
Summary: Herramientas para el terminal de Debian
Home-page: https://linuxdevtips.blogspot.com/
Author: Fernando Enzo Guarini
Author-email: fernandoenzo@gmail.com
Maintainer: 
Maintainer-email: 
License: GPLv3+
Download-URL: https://bitbucket.org/fernandoenzo/terminal/
Keywords: apt debian terminal users
Platform: any
Classifier: Development Status :: 5 - Production/Stable
Classifier: Environment :: Console
Classifier: Intended Audience :: End Users/Desktop
Classifier: License :: OSI Approved :: GNU General Public License v3 or later (GPLv3+)
Classifier: Natural Language :: Spanish
Classifier: Operating System :: POSIX :: Linux
Classifier: Programming Language :: Python :: 3.5
Classifier: Programming Language :: Python :: 3.6
Classifier: Programming Language :: Python :: 3.7
Classifier: Topic :: System :: Installation/Setup
